[
  {
    "clauseID": "@§575-78",
    "rules": [
      {
        "rule": "HEIGHT",
        "args": [
          {
            "key": "MAX",
            "value": "30",
            "units": "FEET"
          }
        ]
      }
    ]
  },
  {
    "clauseID": "@§575-79@A",
    "rules": [
      {
        "rule": "LOT_AREA",
        "args": [
          {
            "key": "SINGLE_FAMILY",
            "value": "TRUE",
            "units": "FLAG"
          },
          {
            "key": "MIN",
            "value": "5000",
            "units": "FEET_SQUARE"
          }
        ]
      },
      {
        "rule": "FRONTAGE",
        "args": [
          {
            "key": "SINGLE_FAMILY",
            "value": "TRUE",
            "units": "FLAG"
          },
          {
            "key": "MIN",
            "value": "50",
            "units": "FEET"
          }
        ]
      }
    ]
  },
  {
    "clauseID": "@§575-79@B",
    "rules": [
      {
        "rule": "LOT_AREA",
        "args": [
          {
            "key": "CORNER_LOT",
            "value": "TRUE",
            "units": "FLAG"
          },
          {
            "key": "SINGLE_FAMILY",
            "value": "TRUE",
            "units": "FLAG"
          },
          {
            "key": "MIN",
            "value": "5500",
            "units": "FEET_SQUARE"
          }
        ]
      }
    ]
  },
  {
    "clauseID": "@§575-80@A",
    "rules": [
      {
        "rule": "LOT_COVERAGE",
        "args": [
          {
            "key": "SINGLE_FAMILY",
            "value": "TRUE",
            "units": "FLAG"
          },
          {
            "key": "MAX",
            "value": "35",
            "units": "PERCENTAGE"
          }
        ]
      }
    ]
  },
  {
    "clauseID": "@§575-81@A@1",
    "rules": [
      {
        "rule": "CODE_CANNOT_BE_TRANSCRIBED",
        "args": []
      }
    ]
  },
  {
    "clauseID": "@§575-81@B@1",
    "rules": [
      {
        "rule": "CODE_CANNOT_BE_TRANSCRIBED",
        "args": []
      }
    ]
  },
  {
    "clauseID": "@§575-83",
    "rules": [
      {
        "rule": "FLOOR_AREA",
        "args": [
          {
            "key": "MIN",
            "value": "1000",
            "units": "FEET_SQUARE"
          }
        ]
      }
    ]
  },
  {
    "clauseID": "@§575-84",
    "rules": [
      {
        "rule": "FRONT_YARD_SETBACK",
        "args": [
          {
            "key": "MAX",
            "value": "35",
            "units": "FEET"
          }
        ]
      }
    ]
  },
  {
    "clauseID": "@§575-85@A",
    "rules": [
      {
        "rule": "CODE_CANNOT_BE_TRANSCRIBED",
        "args": []
      }
    ]
  },
  {
    "clauseID": "@§575-85@B",
    "rules": [
      {
        "rule": "CODE_CANNOT_BE_TRANSCRIBED",
        "args": []
      }
    ]
  },
  {
    "clauseID": "@§575-85@C",
    "rules": [
      {
        "rule": "SIDE_YARD_SETBACK",
        "args": [
          {
            "key": "CORNER_LOT",
            "value": "TRUE",
            "units": "FLAG"
          },
          {
            "key": "TWO_FAMILY",
            "value": "TRUE",
            "units": "FLAG"
          },
          {
            "key": "MULTI_FAMILY",
            "value": "TRUE",
            "units": "FLAG"
          },
          {
            "key": "MIN",
            "value": "20",
            "units": "FEET"
          }
        ]
      }
    ]
  },
  {
    "clauseID": "@§575-85@D",
    "rules": [
      {
        "rule": "SIDE_YARD_SETBACK",
        "args": [
          {
            "key": "TWO_FAMILY",
            "value": "TRUE",
            "units": "FLAG"
          },
          {
            "key": "MULTI_FAMILY",
            "value": "TRUE",
            "units": "FLAG"
          },
          {
            "key": "MIN",
            "value": "20",
            "units": "FEET"
          }
        ]
      }
    ]
  },
  {
    "clauseID": "@§575-86",
    "rules": [
      {
        "rule": "CODE_CANNOT_BE_TRANSCRIBED",
        "args": []
      }
    ]
  },
  {
    "clauseID": "@§575-89@A",
    "rules": [
      {
        "rule": "HEIGHT",
        "args": [
          {
            "key": "ACCESSORY_BUILDING",
            "value": "TRUE",
            "units": "FLAG"
          },
          {
            "key": "MAX",
            "value": "15",
            "units": "FEET"
          }
        ]
      },
      {
        "rule": "REAR_YARD_COVERAGE",
        "args": [
          {
            "key": "ACCESSORY_BUILDING",
            "value": "TRUE",
            "units": "FLAG"
          },
          {
            "key": "MAX",
            "value": "500",
            "units": "FEET_SQUARE"
          },
          {
            "key": "MAX",
            "value": "40",
            "units": "PERCENTAGE"
          }
        ]
      }
    ]
  },
  {
    "clauseID": "@§575-89@B",
    "rules": [
      {
        "rule": "DISTANCE_FROM_MAIN_STRUCTURE",
        "args": [
          {
            "key": "ACCESSORY_BUILDING",
            "value": "TRUE",
            "units": "FLAG"
          },
          {
            "key": "MIN",
            "value": "10",
            "units": "FEET"
          }
        ]
      },
      {
        "rule": "REAR_AND_SIDE_YARD_SETBACK",
        "args": [
          {
            "key": "ACCESSORY_BUILDING",
            "value": "TRUE",
            "units": "FLAG"
          },
          {
            "key": "MIN",
            "value": "3",
            "units": "FEET"
          }
        ]
      }
    ]
  }
]